<?xml version="1.0" encoding="UTF-8"?>
<objects serializationModel="Studio.01.10.00">
    <object class="AudioFile" id="{ac4c7f27-d416-4467-a72b-5256a4189fe5}">
        <property name="assetPath">
            <value>new_content/game/game_10_glitch_short_add_16.ogg</value>
        </property>
        <property name="frequencyInKHz">
            <value>44.0999985</value>
        </property>
        <property name="channelCount">
            <value>2</value>
        </property>
        <property name="length">
            <value>0.20000000000000001</value>
        </property>
        <relationship name="masterAssetFolder">
            <destination>{3a882b8a-30bb-4294-aa44-e27b045f41d2}</destination>
        </relationship>
    </object>
</objects>
