<?xml version="1.0" encoding="UTF-8"?>
<objects serializationModel="Studio.01.10.00">
    <object class="AudioFile" id="{fc39eb7d-4cb8-4e0e-bf95-8b7930e55217}">
        <property name="assetPath">
            <value>character/madeline/main_foley/char_mad_land_03_clutterswitch_03.ogg</value>
        </property>
        <property name="frequencyInKHz">
            <value>44.0999985</value>
        </property>
        <property name="channelCount">
            <value>1</value>
        </property>
        <property name="length">
            <value>0.73142857142857143</value>
        </property>
        <relationship name="masterAssetFolder">
            <destination>{3a882b8a-30bb-4294-aa44-e27b045f41d2}</destination>
        </relationship>
    </object>
</objects>
